[{"id":156901,"url":"https://www.discoveryplus.com/ca/en/shows","name":"Show","countryCode":"CA","group_name":"D+","timestamp":"2026-04-15T02:56:56.926Z","status":200,"responseTime":2055,"success":1,"error":null},
{"id":156900,"url":"https://www.max.com/rohan","name":"Failure","countryCode":"US","group_name":"Max","timestamp":"2026-04-15T02:56:55.709Z","status":404,"responseTime":844,"success":0,"error":"HTTP 404"},
{"id":156899,"url":"https://www.discoveryplus.com/ca/en","name":"Homepage","countryCode":"CA","group_name":"D+","timestamp":"2026-04-15T02:56:55.473Z","status":404,"responseTime":602,"success":0,"error":"HTTP 404"},
{"id":156897,"url":"https://www.max.com/movies","name":"Movie","countryCode":"MX","group_name":"Max","timestamp":"2026-04-15T02:56:55.319Z","status":200,"responseTime":449,"success":1,"error":null},
{"id":156896,"url":"https://www.max.com/mx/es","name":"Homepage","countryCode":"MX","group_name":"Max","timestamp":"2026-04-15T02:56:55.304Z","status":200,"responseTime":436,"success":1,"error":null},
{"id":156895,"url":"https://www.discoveryplus.com/ca/en/movies","name":"Movie","countryCode":"CA","group_name":"D+","timestamp":"2026-04-15T02:56:55.282Z","status":200,"responseTime":410,"success":1,"error":null},
{"id":156893,"url":"https://www.max.com/mx/es/shows","name":"Show","countryCode":"MX","group_name":"Max","timestamp":"2026-04-15T02:56:55.267Z","status":200,"responseTime":398,"success":1,"error":null},
{"id":156894,"url":"https://www.max.com/movies","name":"Movie","countryCode":"US","group_name":"Max","timestamp":"2026-04-15T02:56:55.266Z","status":200,"responseTime":402,"success":1,"error":null},
{"id":156891,"url":"https://www.max.com","name":"Homepage","countryCode":"US","group_name":"Max","timestamp":"2026-04-15T02:56:55.265Z","status":200,"responseTime":444,"success":1,"error":null},
{"id":156892,"url":"https://www.max.com/shows","name":"Show","countryCode":"US","group_name":"Max","timestamp":"2026-04-15T02:56:55.263Z","status":200,"responseTime":400,"success":1,"error":null},
{"id":156898,"url":"https://www.discoveryplus.com/movies","name":"Movie","countryCode":"US","group_name":"D+","timestamp":"2026-04-15T02:56:55.217Z","status":200,"responseTime":350,"success":1,"error":null},
{"id":156890,"url":"https://www.discoveryplus.com","name":"Homepage","countryCode":"US","group_name":"D+","timestamp":"2026-04-15T02:56:55.182Z","status":200,"responseTime":316,"success":1,"error":null},
{"id":156889,"url":"https://www.discoveryplus.com/shows","name":"Show","countryCode":"US","group_name":"D+","timestamp":"2026-04-15T02:56:55.179Z","status":200,"responseTime":312,"success":1,"error":null},
{"id":156888,"url":"https://www.discoveryplus.com/ca/en/shows","name":"Show","countryCode":"CA","group_name":"D+","timestamp":"2026-04-14T23:59:57.049Z","status":200,"responseTime":1456,"success":1,"error":null},
{"id":156887,"url":"https://www.max.com/mx/es/shows","name":"Show","countryCode":"MX","group_name":"Max","timestamp":"2026-04-14T23:59:56.484Z","status":200,"responseTime":895,"success":1,"error":null},
{"id":156886,"url":"https://www.max.com/rohan","name":"Failure","countryCode":"US","group_name":"Max","timestamp":"2026-04-14T23:59:56.339Z","status":404,"responseTime":755,"success":0,"error":"HTTP 404"},
{"id":156885,"url":"https://www.discoveryplus.com/ca/en","name":"Homepage","countryCode":"CA","group_name":"D+","timestamp":"2026-04-14T23:59:56.268Z","status":404,"responseTime":676,"success":0,"error":"HTTP 404"},
{"id":156884,"url":"https://www.max.com/movies","name":"Movie","countryCode":"US","group_name":"Max","timestamp":"2026-04-14T23:59:56.025Z","status":200,"responseTime":443,"success":1,"error":null},
{"id":156883,"url":"https://www.max.com/mx/es","name":"Homepage","countryCode":"MX","group_name":"Max","timestamp":"2026-04-14T23:59:56.023Z","status":200,"responseTime":435,"success":1,"error":null},
{"id":156882,"url":"https://www.max.com/movies","name":"Movie","countryCode":"MX","group_name":"Max","timestamp":"2026-04-14T23:59:56.014Z","status":200,"responseTime":423,"success":1,"error":null},
{"id":156881,"url":"https://www.max.com/shows","name":"Show","countryCode":"US","group_name":"Max","timestamp":"2026-04-14T23:59:56.012Z","status":200,"responseTime":431,"success":1,"error":null},
{"id":156880,"url":"https://www.max.com","name":"Homepage","countryCode":"US","group_name":"Max","timestamp":"2026-04-14T23:59:56.004Z","status":200,"responseTime":477,"success":1,"error":null},
{"id":156879,"url":"https://www.discoveryplus.com","name":"Homepage","countryCode":"US","group_name":"D+","timestamp":"2026-04-14T23:59:55.984Z","status":200,"responseTime":399,"success":1,"error":null},
{"id":156878,"url":"https://www.discoveryplus.com/movies","name":"Movie","countryCode":"US","group_name":"D+","timestamp":"2026-04-14T23:59:55.961Z","status":200,"responseTime":374,"success":1,"error":null},
{"id":156877,"url":"https://www.discoveryplus.com/ca/en/movies","name":"Movie","countryCode":"CA","group_name":"D+","timestamp":"2026-04-14T23:59:55.945Z","status":200,"responseTime":351,"success":1,"error":null},
{"id":156876,"url":"https://www.discoveryplus.com/shows","name":"Show","countryCode":"US","group_name":"D+","timestamp":"2026-04-14T23:59:55.935Z","status":200,"responseTime":349,"success":1,"error":null},
{"id":156875,"url":"https://www.discoveryplus.com/ca/en/shows","name":"Show","countryCode":"CA","group_name":"D+","timestamp":"2026-04-14T23:05:20.815Z","status":200,"responseTime":2224,"success":1,"error":null},
{"id":156874,"url":"https://www.max.com/mx/es/shows","name":"Show","countryCode":"MX","group_name":"Max","timestamp":"2026-04-14T23:05:20.281Z","status":200,"responseTime":1693,"success":1,"error":null},
{"id":156873,"url":"https://www.discoveryplus.com/ca/en/movies","name":"Movie","countryCode":"CA","group_name":"D+","timestamp":"2026-04-14T23:05:19.715Z","status":200,"responseTime":1123,"success":1,"error":null},
{"id":156872,"url":"https://www.discoveryplus.com/ca/en","name":"Homepage","countryCode":"CA","group_name":"D+","timestamp":"2026-04-14T23:05:19.301Z","status":404,"responseTime":711,"success":0,"error":"HTTP 404"},
{"id":156871,"url":"https://www.max.com/rohan","name":"Failure","countryCode":"US","group_name":"Max","timestamp":"2026-04-14T23:05:19.073Z","status":404,"responseTime":491,"success":0,"error":"HTTP 404"},
{"id":156870,"url":"https://www.max.com/mx/es","name":"Homepage","countryCode":"MX","group_name":"Max","timestamp":"2026-04-14T23:05:18.802Z","status":200,"responseTime":215,"success":1,"error":null},
{"id":156869,"url":"https://www.max.com","name":"Homepage","countryCode":"US","group_name":"Max","timestamp":"2026-04-14T23:05:18.794Z","status":200,"responseTime":268,"success":1,"error":null},
{"id":156868,"url":"https://www.discoveryplus.com/shows","name":"Show","countryCode":"US","group_name":"D+","timestamp":"2026-04-14T23:05:18.793Z","status":200,"responseTime":208,"success":1,"error":null},
{"id":156867,"url":"https://www.max.com/shows","name":"Show","countryCode":"US","group_name":"Max","timestamp":"2026-04-14T23:05:18.792Z","status":200,"responseTime":212,"success":1,"error":null},
{"id":156866,"url":"https://www.max.com/movies","name":"Movie","countryCode":"US","group_name":"Max","timestamp":"2026-04-14T23:05:18.787Z","status":200,"responseTime":206,"success":1,"error":null},
{"id":156865,"url":"https://www.max.com/movies","name":"Movie","countryCode":"MX","group_name":"Max","timestamp":"2026-04-14T23:05:18.785Z","status":200,"responseTime":196,"success":1,"error":null},
{"id":156864,"url":"https://www.discoveryplus.com/movies","name":"Movie","countryCode":"US","group_name":"D+","timestamp":"2026-04-14T23:05:18.735Z","status":200,"responseTime":149,"success":1,"error":null},
{"id":156863,"url":"https://www.discoveryplus.com","name":"Homepage","countryCode":"US","group_name":"D+","timestamp":"2026-04-14T23:05:18.729Z","status":200,"responseTime":146,"success":1,"error":null},
{"id":156862,"url":"https://www.discoveryplus.com/ca/en/movies","name":"Movie","countryCode":"CA","group_name":"D+","timestamp":"2026-04-14T22:05:55.851Z","status":200,"responseTime":1540,"success":1,"error":null},
{"id":156861,"url":"https://www.max.com/mx/es/shows","name":"Show","countryCode":"MX","group_name":"Max","timestamp":"2026-04-14T22:05:55.585Z","status":200,"responseTime":1279,"success":1,"error":null},
{"id":156860,"url":"https://www.max.com/shows","name":"Show","countryCode":"US","group_name":"Max","timestamp":"2026-04-14T22:05:55.231Z","status":200,"responseTime":932,"success":1,"error":null},
{"id":156859,"url":"https://www.discoveryplus.com/ca/en/shows","name":"Show","countryCode":"CA","group_name":"D+","timestamp":"2026-04-14T22:05:55.208Z","status":200,"responseTime":898,"success":1,"error":null},
{"id":156858,"url":"https://www.discoveryplus.com/ca/en","name":"Homepage","countryCode":"CA","group_name":"D+","timestamp":"2026-04-14T22:05:54.853Z","status":404,"responseTime":544,"success":0,"error":"HTTP 404"},
{"id":156857,"url":"https://www.max.com/rohan","name":"Failure","countryCode":"US","group_name":"Max","timestamp":"2026-04-14T22:05:54.844Z","status":404,"responseTime":543,"success":0,"error":"HTTP 404"},
{"id":156856,"url":"https://www.max.com/movies","name":"Movie","countryCode":"MX","group_name":"Max","timestamp":"2026-04-14T22:05:54.657Z","status":200,"responseTime":349,"success":1,"error":null},
{"id":156855,"url":"https://www.max.com/mx/es","name":"Homepage","countryCode":"MX","group_name":"Max","timestamp":"2026-04-14T22:05:54.627Z","status":200,"responseTime":322,"success":1,"error":null},
{"id":156854,"url":"https://www.max.com/movies","name":"Movie","countryCode":"US","group_name":"Max","timestamp":"2026-04-14T22:05:54.623Z","status":200,"responseTime":323,"success":1,"error":null},
{"id":156853,"url":"https://www.max.com","name":"Homepage","countryCode":"US","group_name":"Max","timestamp":"2026-04-14T22:05:54.596Z","status":200,"responseTime":350,"success":1,"error":null},
{"id":156852,"url":"https://www.discoveryplus.com/shows","name":"Show","countryCode":"US","group_name":"D+","timestamp":"2026-04-14T22:05:54.558Z","status":200,"responseTime":255,"success":1,"error":null},
{"id":156851,"url":"https://www.discoveryplus.com/movies","name":"Movie","countryCode":"US","group_name":"D+","timestamp":"2026-04-14T22:05:54.515Z","status":200,"responseTime":211,"success":1,"error":null},
{"id":156850,"url":"https://www.discoveryplus.com","name":"Homepage","countryCode":"US","group_name":"D+","timestamp":"2026-04-14T22:05:54.497Z","status":200,"responseTime":195,"success":1,"error":null},
{"id":156849,"url":"https://www.discoveryplus.com/ca/en/shows","name":"Show","countryCode":"CA","group_name":"D+","timestamp":"2026-04-14T21:10:24.452Z","status":200,"responseTime":1621,"success":1,"error":null},
{"id":156848,"url":"https://www.max.com/mx/es/shows","name":"Show","countryCode":"MX","group_name":"Max","timestamp":"2026-04-14T21:10:23.587Z","status":200,"responseTime":760,"success":1,"error":null},
{"id":156847,"url":"https://www.max.com/rohan","name":"Failure","countryCode":"US","group_name":"Max","timestamp":"2026-04-14T21:10:23.492Z","status":404,"responseTime":670,"success":0,"error":"HTTP 404"},
{"id":156846,"url":"https://www.discoveryplus.com/ca/en","name":"Homepage","countryCode":"CA","group_name":"D+","timestamp":"2026-04-14T21:10:23.425Z","status":404,"responseTime":595,"success":0,"error":"HTTP 404"},
{"id":156845,"url":"https://www.max.com/movies","name":"Movie","countryCode":"US","group_name":"Max","timestamp":"2026-04-14T21:10:23.250Z","status":200,"responseTime":430,"success":1,"error":null},
{"id":156844,"url":"https://www.max.com/movies","name":"Movie","countryCode":"MX","group_name":"Max","timestamp":"2026-04-14T21:10:23.194Z","status":200,"responseTime":365,"success":1,"error":null},
{"id":156843,"url":"https://www.max.com/mx/es","name":"Homepage","countryCode":"MX","group_name":"Max","timestamp":"2026-04-14T21:10:23.192Z","status":200,"responseTime":366,"success":1,"error":null},
{"id":156842,"url":"https://www.max.com/shows","name":"Show","countryCode":"US","group_name":"Max","timestamp":"2026-04-14T21:10:23.178Z","status":200,"responseTime":360,"success":1,"error":null},
{"id":156841,"url":"https://www.max.com","name":"Homepage","countryCode":"US","group_name":"Max","timestamp":"2026-04-14T21:10:23.144Z","status":200,"responseTime":381,"success":1,"error":null},
{"id":156840,"url":"https://www.discoveryplus.com/shows","name":"Show","countryCode":"US","group_name":"D+","timestamp":"2026-04-14T21:10:23.127Z","status":200,"responseTime":303,"success":1,"error":null},
{"id":156839,"url":"https://www.discoveryplus.com/ca/en/movies","name":"Movie","countryCode":"CA","group_name":"D+","timestamp":"2026-04-14T21:10:23.110Z","status":200,"responseTime":278,"success":1,"error":null},
{"id":156838,"url":"https://www.discoveryplus.com/movies","name":"Movie","countryCode":"US","group_name":"D+","timestamp":"2026-04-14T21:10:23.109Z","status":200,"responseTime":284,"success":1,"error":null},
{"id":156837,"url":"https://www.discoveryplus.com","name":"Homepage","countryCode":"US","group_name":"D+","timestamp":"2026-04-14T21:10:23.106Z","status":200,"responseTime":283,"success":1,"error":null},
{"id":156836,"url":"https://www.max.com/rohan","name":"Failure","countryCode":"US","group_name":"Max","timestamp":"2026-04-14T20:16:15.455Z","status":404,"responseTime":827,"success":0,"error":"HTTP 404"},
{"id":156835,"url":"https://www.discoveryplus.com/ca/en/shows","name":"Show","countryCode":"CA","group_name":"D+","timestamp":"2026-04-14T20:16:15.350Z","status":200,"responseTime":713,"success":1,"error":null},
{"id":156834,"url":"https://www.discoveryplus.com/ca/en","name":"Homepage","countryCode":"CA","group_name":"D+","timestamp":"2026-04-14T20:16:15.328Z","status":404,"responseTime":692,"success":0,"error":"HTTP 404"},
{"id":156833,"url":"https://www.discoveryplus.com/shows","name":"Show","countryCode":"US","group_name":"D+","timestamp":"2026-04-14T20:16:15.235Z","status":200,"responseTime":605,"success":1,"error":null},
{"id":156832,"url":"https://www.max.com/movies","name":"Movie","countryCode":"US","group_name":"Max","timestamp":"2026-04-14T20:16:15.126Z","status":200,"responseTime":500,"success":1,"error":null},
{"id":156831,"url":"https://www.max.com/mx/es/shows","name":"Show","countryCode":"MX","group_name":"Max","timestamp":"2026-04-14T20:16:15.105Z","status":200,"responseTime":471,"success":1,"error":null},
{"id":156830,"url":"https://www.max.com/shows","name":"Show","countryCode":"US","group_name":"Max","timestamp":"2026-04-14T20:16:15.071Z","status":200,"responseTime":446,"success":1,"error":null},
{"id":156829,"url":"https://www.max.com/movies","name":"Movie","countryCode":"MX","group_name":"Max","timestamp":"2026-04-14T20:16:15.063Z","status":200,"responseTime":428,"success":1,"error":null},
{"id":156828,"url":"https://www.max.com","name":"Homepage","countryCode":"US","group_name":"Max","timestamp":"2026-04-14T20:16:15.061Z","status":200,"responseTime":490,"success":1,"error":null},
{"id":156827,"url":"https://www.max.com/mx/es","name":"Homepage","countryCode":"MX","group_name":"Max","timestamp":"2026-04-14T20:16:15.054Z","status":200,"responseTime":421,"success":1,"error":null},
{"id":156826,"url":"https://www.discoveryplus.com/movies","name":"Movie","countryCode":"US","group_name":"D+","timestamp":"2026-04-14T20:16:14.961Z","status":200,"responseTime":329,"success":1,"error":null},
{"id":156825,"url":"https://www.discoveryplus.com/ca/en/movies","name":"Movie","countryCode":"CA","group_name":"D+","timestamp":"2026-04-14T20:16:14.954Z","status":200,"responseTime":316,"success":1,"error":null},
{"id":156824,"url":"https://www.discoveryplus.com","name":"Homepage","countryCode":"US","group_name":"D+","timestamp":"2026-04-14T20:16:14.948Z","status":200,"responseTime":319,"success":1,"error":null},
{"id":156823,"url":"https://www.discoveryplus.com/ca/en/shows","name":"Show","countryCode":"CA","group_name":"D+","timestamp":"2026-04-14T19:09:26.229Z","status":200,"responseTime":1477,"success":1,"error":null},
{"id":156822,"url":"https://www.discoveryplus.com/shows","name":"Show","countryCode":"US","group_name":"D+","timestamp":"2026-04-14T19:09:25.519Z","status":200,"responseTime":774,"success":1,"error":null},
{"id":156821,"url":"https://www.max.com/rohan","name":"Failure","countryCode":"US","group_name":"Max","timestamp":"2026-04-14T19:09:25.482Z","status":404,"responseTime":739,"success":0,"error":"HTTP 404"},
{"id":156820,"url":"https://www.discoveryplus.com/ca/en","name":"Homepage","countryCode":"CA","group_name":"D+","timestamp":"2026-04-14T19:09:25.374Z","status":404,"responseTime":624,"success":0,"error":"HTTP 404"},
{"id":156819,"url":"https://www.max.com/mx/es/shows","name":"Show","countryCode":"MX","group_name":"Max","timestamp":"2026-04-14T19:09:25.200Z","status":200,"responseTime":452,"success":1,"error":null},
{"id":156818,"url":"https://www.max.com/shows","name":"Show","countryCode":"US","group_name":"Max","timestamp":"2026-04-14T19:09:25.176Z","status":200,"responseTime":436,"success":1,"error":null},
{"id":156817,"url":"https://www.max.com/mx/es","name":"Homepage","countryCode":"MX","group_name":"Max","timestamp":"2026-04-14T19:09:25.156Z","status":200,"responseTime":409,"success":1,"error":null},
{"id":156816,"url":"https://www.max.com","name":"Homepage","countryCode":"US","group_name":"Max","timestamp":"2026-04-14T19:09:25.154Z","status":200,"responseTime":468,"success":1,"error":null},
{"id":156815,"url":"https://www.max.com/movies","name":"Movie","countryCode":"US","group_name":"Max","timestamp":"2026-04-14T19:09:25.151Z","status":200,"responseTime":410,"success":1,"error":null},
{"id":156814,"url":"https://www.max.com/movies","name":"Movie","countryCode":"MX","group_name":"Max","timestamp":"2026-04-14T19:09:25.149Z","status":200,"responseTime":400,"success":1,"error":null},
{"id":156813,"url":"https://www.discoveryplus.com/movies","name":"Movie","countryCode":"US","group_name":"D+","timestamp":"2026-04-14T19:09:25.074Z","status":200,"responseTime":328,"success":1,"error":null},
{"id":156812,"url":"https://www.discoveryplus.com","name":"Homepage","countryCode":"US","group_name":"D+","timestamp":"2026-04-14T19:09:25.061Z","status":200,"responseTime":317,"success":1,"error":null},
{"id":156811,"url":"https://www.discoveryplus.com/ca/en/movies","name":"Movie","countryCode":"CA","group_name":"D+","timestamp":"2026-04-14T19:09:25.059Z","status":200,"responseTime":306,"success":1,"error":null},
{"id":156810,"url":"https://www.discoveryplus.com/ca/en/shows","name":"Show","countryCode":"CA","group_name":"D+","timestamp":"2026-04-14T17:53:31.452Z","status":200,"responseTime":1536,"success":1,"error":null},
{"id":156809,"url":"https://www.discoveryplus.com/ca/en/movies","name":"Movie","countryCode":"CA","group_name":"D+","timestamp":"2026-04-14T17:53:31.130Z","status":200,"responseTime":1213,"success":1,"error":null},
{"id":156808,"url":"https://www.max.com/rohan","name":"Failure","countryCode":"US","group_name":"Max","timestamp":"2026-04-14T17:53:30.662Z","status":404,"responseTime":757,"success":0,"error":"HTTP 404"},
{"id":156807,"url":"https://www.max.com/mx/es/shows","name":"Show","countryCode":"MX","group_name":"Max","timestamp":"2026-04-14T17:53:30.641Z","status":200,"responseTime":729,"success":1,"error":null},
{"id":156806,"url":"https://www.max.com/shows","name":"Show","countryCode":"US","group_name":"Max","timestamp":"2026-04-14T17:53:30.487Z","status":200,"responseTime":585,"success":1,"error":null},
{"id":156805,"url":"https://www.discoveryplus.com/ca/en","name":"Homepage","countryCode":"CA","group_name":"D+","timestamp":"2026-04-14T17:53:30.409Z","status":404,"responseTime":494,"success":0,"error":"HTTP 404"},
{"id":156804,"url":"https://www.max.com/mx/es","name":"Homepage","countryCode":"MX","group_name":"Max","timestamp":"2026-04-14T17:53:30.365Z","status":200,"responseTime":455,"success":1,"error":null},
{"id":156803,"url":"https://www.max.com","name":"Homepage","countryCode":"US","group_name":"Max","timestamp":"2026-04-14T17:53:30.364Z","status":200,"responseTime":518,"success":1,"error":null},
{"id":156802,"url":"https://www.max.com/movies","name":"Movie","countryCode":"US","group_name":"Max","timestamp":"2026-04-14T17:53:30.345Z","status":200,"responseTime":442,"success":1,"error":null},
{"id":156801,"url":"https://www.max.com/movies","name":"Movie","countryCode":"MX","group_name":"Max","timestamp":"2026-04-14T17:53:30.333Z","status":200,"responseTime":420,"success":1,"error":null},
{"id":156800,"url":"https://www.discoveryplus.com","name":"Homepage","countryCode":"US","group_name":"D+","timestamp":"2026-04-14T17:53:30.306Z","status":200,"responseTime":400,"success":1,"error":null},
{"id":156799,"url":"https://www.discoveryplus.com/shows","name":"Show","countryCode":"US","group_name":"D+","timestamp":"2026-04-14T17:53:30.273Z","status":200,"responseTime":365,"success":1,"error":null},
{"id":156798,"url":"https://www.discoveryplus.com/movies","name":"Movie","countryCode":"US","group_name":"D+","timestamp":"2026-04-14T17:53:30.255Z","status":200,"responseTime":346,"success":1,"error":null},
{"id":156797,"url":"https://www.discoveryplus.com/ca/en/shows","name":"Show","countryCode":"CA","group_name":"D+","timestamp":"2026-04-14T16:46:18.717Z","status":200,"responseTime":1618,"success":1,"error":null},
{"id":156796,"url":"https://www.max.com/mx/es/shows","name":"Show","countryCode":"MX","group_name":"Max","timestamp":"2026-04-14T16:46:17.945Z","status":200,"responseTime":850,"success":1,"error":null},
{"id":156795,"url":"https://www.discoveryplus.com/ca/en","name":"Homepage","countryCode":"CA","group_name":"D+","timestamp":"2026-04-14T16:46:17.764Z","status":404,"responseTime":666,"success":0,"error":"HTTP 404"},
{"id":156794,"url":"https://www.max.com/rohan","name":"Failure","countryCode":"US","group_name":"Max","timestamp":"2026-04-14T16:46:17.592Z","status":404,"responseTime":503,"success":0,"error":"HTTP 404"},
{"id":156793,"url":"https://www.max.com/mx/es","name":"Homepage","countryCode":"MX","group_name":"Max","timestamp":"2026-04-14T16:46:17.544Z","status":200,"responseTime":450,"success":1,"error":null},
{"id":156792,"url":"https://www.max.com/movies","name":"Movie","countryCode":"MX","group_name":"Max","timestamp":"2026-04-14T16:46:17.520Z","status":200,"responseTime":424,"success":1,"error":null},
{"id":156791,"url":"https://www.discoveryplus.com","name":"Homepage","countryCode":"US","group_name":"D+","timestamp":"2026-04-14T16:46:17.466Z","status":200,"responseTime":376,"success":1,"error":null},
{"id":156790,"url":"https://www.discoveryplus.com/ca/en/movies","name":"Movie","countryCode":"CA","group_name":"D+","timestamp":"2026-04-14T16:46:17.464Z","status":200,"responseTime":364,"success":1,"error":null},
{"id":156789,"url":"https://www.discoveryplus.com/shows","name":"Show","countryCode":"US","group_name":"D+","timestamp":"2026-04-14T16:46:17.449Z","status":200,"responseTime":358,"success":1,"error":null},
{"id":156788,"url":"https://www.discoveryplus.com/movies","name":"Movie","countryCode":"US","group_name":"D+","timestamp":"2026-04-14T16:46:17.435Z","status":200,"responseTime":342,"success":1,"error":null},
{"id":156787,"url":"https://www.max.com","name":"Homepage","countryCode":"US","group_name":"Max","timestamp":"2026-04-14T16:46:17.421Z","status":200,"responseTime":390,"success":1,"error":null},
{"id":156786,"url":"https://www.max.com/shows","name":"Show","countryCode":"US","group_name":"Max","timestamp":"2026-04-14T16:46:17.396Z","status":200,"responseTime":310,"success":1,"error":null},
{"id":156785,"url":"https://www.max.com/movies","name":"Movie","countryCode":"US","group_name":"Max","timestamp":"2026-04-14T16:46:17.394Z","status":200,"responseTime":305,"success":1,"error":null},
{"id":156784,"url":"https://www.discoveryplus.com/ca/en/shows","name":"Show","countryCode":"CA","group_name":"D+","timestamp":"2026-04-14T15:41:23.665Z","status":200,"responseTime":1790,"success":1,"error":null},
{"id":156783,"url":"https://www.discoveryplus.com/ca/en/movies","name":"Movie","countryCode":"CA","group_name":"D+","timestamp":"2026-04-14T15:41:23.068Z","status":200,"responseTime":1192,"success":1,"error":null},
{"id":156782,"url":"https://www.max.com/rohan","name":"Failure","countryCode":"US","group_name":"Max","timestamp":"2026-04-14T15:41:22.529Z","status":404,"responseTime":663,"success":0,"error":"HTTP 404"},
{"id":156781,"url":"https://www.discoveryplus.com/ca/en","name":"Homepage","countryCode":"CA","group_name":"D+","timestamp":"2026-04-14T15:41:22.489Z","status":404,"responseTime":615,"success":0,"error":"HTTP 404"},
{"id":156780,"url":"https://www.max.com/mx/es/shows","name":"Show","countryCode":"MX","group_name":"Max","timestamp":"2026-04-14T15:41:22.302Z","status":200,"responseTime":431,"success":1,"error":null},
{"id":156779,"url":"https://www.max.com/shows","name":"Show","countryCode":"US","group_name":"Max","timestamp":"2026-04-14T15:41:22.299Z","status":200,"responseTime":436,"success":1,"error":null},
{"id":156778,"url":"https://www.max.com/movies","name":"Movie","countryCode":"MX","group_name":"Max","timestamp":"2026-04-14T15:41:22.284Z","status":200,"responseTime":411,"success":1,"error":null},
{"id":156777,"url":"https://www.max.com","name":"Homepage","countryCode":"US","group_name":"Max","timestamp":"2026-04-14T15:41:22.281Z","status":200,"responseTime":471,"success":1,"error":null},
{"id":156776,"url":"https://www.max.com/mx/es","name":"Homepage","countryCode":"MX","group_name":"Max","timestamp":"2026-04-14T15:41:22.279Z","status":200,"responseTime":409,"success":1,"error":null},
{"id":156775,"url":"https://www.max.com/movies","name":"Movie","countryCode":"US","group_name":"Max","timestamp":"2026-04-14T15:41:22.274Z","status":200,"responseTime":409,"success":1,"error":null},
{"id":156774,"url":"https://www.discoveryplus.com/movies","name":"Movie","countryCode":"US","group_name":"D+","timestamp":"2026-04-14T15:41:22.258Z","status":200,"responseTime":389,"success":1,"error":null},
{"id":156773,"url":"https://www.discoveryplus.com","name":"Homepage","countryCode":"US","group_name":"D+","timestamp":"2026-04-14T15:41:22.250Z","status":200,"responseTime":383,"success":1,"error":null},
{"id":156772,"url":"https://www.discoveryplus.com/shows","name":"Show","countryCode":"US","group_name":"D+","timestamp":"2026-04-14T15:41:22.189Z","status":200,"responseTime":321,"success":1,"error":null},
{"id":156771,"url":"https://www.max.com/rohan","name":"Failure","countryCode":"US","group_name":"Max","timestamp":"2026-04-14T14:13:59.475Z","status":404,"responseTime":729,"success":0,"error":"HTTP 404"},
{"id":156770,"url":"https://www.max.com/mx/es","name":"Homepage","countryCode":"MX","group_name":"Max","timestamp":"2026-04-14T14:13:59.306Z","status":200,"responseTime":555,"success":1,"error":null},
{"id":156769,"url":"https://www.discoveryplus.com/ca/en","name":"Homepage","countryCode":"CA","group_name":"D+","timestamp":"2026-04-14T14:13:59.298Z","status":404,"responseTime":544,"success":0,"error":"HTTP 404"},
{"id":156768,"url":"https://www.max.com","name":"Homepage","countryCode":"US","group_name":"Max","timestamp":"2026-04-14T14:13:59.287Z","status":200,"responseTime":598,"success":1,"error":null},
{"id":156767,"url":"https://www.max.com/mx/es/shows","name":"Show","countryCode":"MX","group_name":"Max","timestamp":"2026-04-14T14:13:59.216Z","status":200,"responseTime":464,"success":1,"error":null},
{"id":156766,"url":"https://www.max.com/movies","name":"Movie","countryCode":"MX","group_name":"Max","timestamp":"2026-04-14T14:13:59.196Z","status":200,"responseTime":443,"success":1,"error":null},
{"id":156765,"url":"https://www.max.com/movies","name":"Movie","countryCode":"US","group_name":"Max","timestamp":"2026-04-14T14:13:59.146Z","status":200,"responseTime":401,"success":1,"error":null},
{"id":156764,"url":"https://www.max.com/shows","name":"Show","countryCode":"US","group_name":"Max","timestamp":"2026-04-14T14:13:59.124Z","status":200,"responseTime":380,"success":1,"error":null},
{"id":156763,"url":"https://www.discoveryplus.com/ca/en/movies","name":"Movie","countryCode":"CA","group_name":"D+","timestamp":"2026-04-14T14:13:59.091Z","status":200,"responseTime":335,"success":1,"error":null},
{"id":156762,"url":"https://www.discoveryplus.com/ca/en/shows","name":"Show","countryCode":"CA","group_name":"D+","timestamp":"2026-04-14T14:13:59.090Z","status":200,"responseTime":335,"success":1,"error":null},
{"id":156761,"url":"https://www.discoveryplus.com/movies","name":"Movie","countryCode":"US","group_name":"D+","timestamp":"2026-04-14T14:13:59.088Z","status":200,"responseTime":338,"success":1,"error":null},
{"id":156760,"url":"https://www.discoveryplus.com/shows","name":"Show","countryCode":"US","group_name":"D+","timestamp":"2026-04-14T14:13:59.081Z","status":200,"responseTime":332,"success":1,"error":null},
{"id":156759,"url":"https://www.discoveryplus.com","name":"Homepage","countryCode":"US","group_name":"D+","timestamp":"2026-04-14T14:13:59.048Z","status":200,"responseTime":301,"success":1,"error":null},
{"id":156758,"url":"https://www.discoveryplus.com/ca/en/shows","name":"Show","countryCode":"CA","group_name":"D+","timestamp":"2026-04-14T12:13:12.822Z","status":200,"responseTime":1260,"success":1,"error":null},
{"id":156757,"url":"https://www.max.com/rohan","name":"Failure","countryCode":"US","group_name":"Max","timestamp":"2026-04-14T12:13:12.291Z","status":404,"responseTime":738,"success":0,"error":"HTTP 404"},
{"id":156756,"url":"https://www.discoveryplus.com/ca/en","name":"Homepage","countryCode":"CA","group_name":"D+","timestamp":"2026-04-14T12:13:12.187Z","status":404,"responseTime":626,"success":0,"error":"HTTP 404"},
{"id":156755,"url":"https://www.max.com/mx/es/shows","name":"Show","countryCode":"MX","group_name":"Max","timestamp":"2026-04-14T12:13:12.136Z","status":200,"responseTime":577,"success":1,"error":null},
{"id":156754,"url":"https://www.max.com/mx/es","name":"Homepage","countryCode":"MX","group_name":"Max","timestamp":"2026-04-14T12:13:11.809Z","status":200,"responseTime":251,"success":1,"error":null},
{"id":156753,"url":"https://www.discoveryplus.com/shows","name":"Show","countryCode":"US","group_name":"D+","timestamp":"2026-04-14T12:13:11.799Z","status":200,"responseTime":244,"success":1,"error":null},
{"id":156752,"url":"https://www.discoveryplus.com/ca/en/movies","name":"Movie","countryCode":"CA","group_name":"D+","timestamp":"2026-04-14T12:13:11.798Z","status":200,"responseTime":235,"success":1,"error":null},
{"id":156751,"url":"https://www.discoveryplus.com/movies","name":"Movie","countryCode":"US","group_name":"D+","timestamp":"2026-04-14T12:13:11.795Z","status":200,"responseTime":238,"success":1,"error":null},
{"id":156750,"url":"https://www.max.com/movies","name":"Movie","countryCode":"MX","group_name":"Max","timestamp":"2026-04-14T12:13:11.784Z","status":200,"responseTime":224,"success":1,"error":null},
{"id":156749,"url":"https://www.max.com","name":"Homepage","countryCode":"US","group_name":"Max","timestamp":"2026-04-14T12:13:11.765Z","status":200,"responseTime":270,"success":1,"error":null},
{"id":156748,"url":"https://www.max.com/shows","name":"Show","countryCode":"US","group_name":"Max","timestamp":"2026-04-14T12:13:11.756Z","status":200,"responseTime":206,"success":1,"error":null},
{"id":156747,"url":"https://www.max.com/movies","name":"Movie","countryCode":"US","group_name":"Max","timestamp":"2026-04-14T12:13:11.744Z","status":200,"responseTime":192,"success":1,"error":null},
{"id":156746,"url":"https://www.discoveryplus.com","name":"Homepage","countryCode":"US","group_name":"D+","timestamp":"2026-04-14T12:13:11.734Z","status":200,"responseTime":180,"success":1,"error":null},
{"id":156745,"url":"https://www.discoveryplus.com/ca/en/shows","name":"Show","countryCode":"CA","group_name":"D+","timestamp":"2026-04-14T11:21:05.458Z","status":200,"responseTime":1461,"success":1,"error":null},
{"id":156744,"url":"https://www.max.com/rohan","name":"Failure","countryCode":"US","group_name":"Max","timestamp":"2026-04-14T11:21:04.919Z","status":404,"responseTime":932,"success":0,"error":"HTTP 404"},
{"id":156743,"url":"https://www.discoveryplus.com/ca/en","name":"Homepage","countryCode":"CA","group_name":"D+","timestamp":"2026-04-14T11:21:04.518Z","status":404,"responseTime":522,"success":0,"error":"HTTP 404"},
{"id":156742,"url":"https://www.max.com/mx/es","name":"Homepage","countryCode":"MX","group_name":"Max","timestamp":"2026-04-14T11:21:04.452Z","status":200,"responseTime":460,"success":1,"error":null},
{"id":156741,"url":"https://www.max.com","name":"Homepage","countryCode":"US","group_name":"Max","timestamp":"2026-04-14T11:21:04.433Z","status":200,"responseTime":503,"success":1,"error":null},
{"id":156740,"url":"https://www.max.com/movies","name":"Movie","countryCode":"US","group_name":"Max","timestamp":"2026-04-14T11:21:04.384Z","status":200,"responseTime":398,"success":1,"error":null},
{"id":156739,"url":"https://www.max.com/shows","name":"Show","countryCode":"US","group_name":"Max","timestamp":"2026-04-14T11:21:04.380Z","status":200,"responseTime":396,"success":1,"error":null},
{"id":156738,"url":"https://www.max.com/mx/es/shows","name":"Show","countryCode":"MX","group_name":"Max","timestamp":"2026-04-14T11:21:04.369Z","status":200,"responseTime":376,"success":1,"error":null},
{"id":156737,"url":"https://www.discoveryplus.com/shows","name":"Show","countryCode":"US","group_name":"D+","timestamp":"2026-04-14T11:21:04.358Z","status":200,"responseTime":368,"success":1,"error":null},
{"id":156736,"url":"https://www.max.com/movies","name":"Movie","countryCode":"MX","group_name":"Max","timestamp":"2026-04-14T11:21:04.339Z","status":200,"responseTime":344,"success":1,"error":null},
{"id":156735,"url":"https://www.discoveryplus.com/ca/en/movies","name":"Movie","countryCode":"CA","group_name":"D+","timestamp":"2026-04-14T11:21:04.335Z","status":200,"responseTime":337,"success":1,"error":null},
{"id":156734,"url":"https://www.discoveryplus.com/movies","name":"Movie","countryCode":"US","group_name":"D+","timestamp":"2026-04-14T11:21:04.332Z","status":200,"responseTime":341,"success":1,"error":null},
{"id":156733,"url":"https://www.discoveryplus.com","name":"Homepage","countryCode":"US","group_name":"D+","timestamp":"2026-04-14T11:21:04.241Z","status":200,"responseTime":251,"success":1,"error":null},
{"id":156732,"url":"https://www.max.com/rohan","name":"Failure","countryCode":"US","group_name":"Max","timestamp":"2026-04-14T10:13:51.410Z","status":404,"responseTime":1218,"success":0,"error":"HTTP 404"},
{"id":156731,"url":"https://www.discoveryplus.com/ca/en","name":"Homepage","countryCode":"CA","group_name":"D+","timestamp":"2026-04-14T10:13:50.909Z","status":404,"responseTime":709,"success":0,"error":"HTTP 404"},
{"id":156730,"url":"https://www.max.com/mx/es/shows","name":"Show","countryCode":"MX","group_name":"Max","timestamp":"2026-04-14T10:13:50.749Z","status":200,"responseTime":552,"success":1,"error":null},
{"id":156729,"url":"https://www.max.com/shows","name":"Show","countryCode":"US","group_name":"Max","timestamp":"2026-04-14T10:13:50.738Z","status":200,"responseTime":549,"success":1,"error":null},
{"id":156728,"url":"https://www.max.com/mx/es","name":"Homepage","countryCode":"MX","group_name":"Max","timestamp":"2026-04-14T10:13:50.720Z","status":200,"responseTime":523,"success":1,"error":null},
{"id":156727,"url":"https://www.max.com","name":"Homepage","countryCode":"US","group_name":"Max","timestamp":"2026-04-14T10:13:50.715Z","status":200,"responseTime":579,"success":1,"error":null},
{"id":156726,"url":"https://www.max.com/movies","name":"Movie","countryCode":"MX","group_name":"Max","timestamp":"2026-04-14T10:13:50.713Z","status":200,"responseTime":514,"success":1,"error":null},
{"id":156725,"url":"https://www.max.com/movies","name":"Movie","countryCode":"US","group_name":"Max","timestamp":"2026-04-14T10:13:50.695Z","status":200,"responseTime":504,"success":1,"error":null},
{"id":156724,"url":"https://www.discoveryplus.com/ca/en/movies","name":"Movie","countryCode":"CA","group_name":"D+","timestamp":"2026-04-14T10:13:50.594Z","status":200,"responseTime":392,"success":1,"error":null},
{"id":156723,"url":"https://www.discoveryplus.com/ca/en/shows","name":"Show","countryCode":"CA","group_name":"D+","timestamp":"2026-04-14T10:13:50.584Z","status":200,"responseTime":383,"success":1,"error":null},
{"id":156722,"url":"https://www.discoveryplus.com/shows","name":"Show","countryCode":"US","group_name":"D+","timestamp":"2026-04-14T10:13:50.582Z","status":200,"responseTime":388,"success":1,"error":null},
{"id":156721,"url":"https://www.discoveryplus.com/movies","name":"Movie","countryCode":"US","group_name":"D+","timestamp":"2026-04-14T10:13:50.576Z","status":200,"responseTime":381,"success":1,"error":null},
{"id":156720,"url":"https://www.discoveryplus.com","name":"Homepage","countryCode":"US","group_name":"D+","timestamp":"2026-04-14T10:13:50.573Z","status":200,"responseTime":380,"success":1,"error":null},
{"id":156719,"url":"https://www.discoveryplus.com/ca/en/shows","name":"Show","countryCode":"CA","group_name":"D+","timestamp":"2026-04-14T08:54:14.031Z","status":200,"responseTime":1486,"success":1,"error":null},
{"id":156718,"url":"https://www.max.com/rohan","name":"Failure","countryCode":"US","group_name":"Max","timestamp":"2026-04-14T08:54:13.413Z","status":404,"responseTime":878,"success":0,"error":"HTTP 404"},
{"id":156717,"url":"https://www.max.com/shows","name":"Show","countryCode":"US","group_name":"Max","timestamp":"2026-04-14T08:54:13.177Z","status":200,"responseTime":644,"success":1,"error":null},
{"id":156716,"url":"https://www.max.com/mx/es","name":"Homepage","countryCode":"MX","group_name":"Max","timestamp":"2026-04-14T08:54:13.143Z","status":200,"responseTime":603,"success":1,"error":null},
{"id":156715,"url":"https://www.max.com","name":"Homepage","countryCode":"US","group_name":"Max","timestamp":"2026-04-14T08:54:13.142Z","status":200,"responseTime":663,"success":1,"error":null},
{"id":156714,"url":"https://www.discoveryplus.com/ca/en","name":"Homepage","countryCode":"CA","group_name":"D+","timestamp":"2026-04-14T08:54:13.138Z","status":404,"responseTime":595,"success":0,"error":"HTTP 404"},
{"id":156713,"url":"https://www.discoveryplus.com/shows","name":"Show","countryCode":"US","group_name":"D+","timestamp":"2026-04-14T08:54:13.054Z","status":200,"responseTime":516,"success":1,"error":null},
{"id":156712,"url":"https://www.max.com/movies","name":"Movie","countryCode":"US","group_name":"Max","timestamp":"2026-04-14T08:54:13.011Z","status":200,"responseTime":477,"success":1,"error":null},
{"id":156711,"url":"https://www.max.com/mx/es/shows","name":"Show","countryCode":"MX","group_name":"Max","timestamp":"2026-04-14T08:54:12.996Z","status":200,"responseTime":455,"success":1,"error":null},
{"id":156710,"url":"https://www.max.com/movies","name":"Movie","countryCode":"MX","group_name":"Max","timestamp":"2026-04-14T08:54:12.989Z","status":200,"responseTime":447,"success":1,"error":null},
{"id":156709,"url":"https://www.discoveryplus.com/ca/en/movies","name":"Movie","countryCode":"CA","group_name":"D+","timestamp":"2026-04-14T08:54:12.964Z","status":200,"responseTime":418,"success":1,"error":null},
{"id":156708,"url":"https://www.discoveryplus.com/movies","name":"Movie","countryCode":"US","group_name":"D+","timestamp":"2026-04-14T08:54:12.850Z","status":200,"responseTime":311,"success":1,"error":null},
{"id":156707,"url":"https://www.discoveryplus.com","name":"Homepage","countryCode":"US","group_name":"D+","timestamp":"2026-04-14T08:54:12.848Z","status":200,"responseTime":311,"success":1,"error":null},
{"id":156706,"url":"https://www.discoveryplus.com/ca/en/shows","name":"Show","countryCode":"CA","group_name":"D+","timestamp":"2026-04-14T07:12:26.922Z","status":200,"responseTime":1591,"success":1,"error":null},
{"id":156705,"url":"https://www.discoveryplus.com/shows","name":"Show","countryCode":"US","group_name":"D+","timestamp":"2026-04-14T07:12:26.174Z","status":200,"responseTime":850,"success":1,"error":null},
{"id":156704,"url":"https://www.max.com/shows","name":"Show","countryCode":"US","group_name":"Max","timestamp":"2026-04-14T07:12:26.105Z","status":200,"responseTime":786,"success":1,"error":null},
{"id":156703,"url":"https://www.max.com/mx/es/shows","name":"Show","countryCode":"MX","group_name":"Max","timestamp":"2026-04-14T07:12:26.053Z","status":200,"responseTime":726,"success":1,"error":null},
{"id":156702,"url":"https://www.max.com/rohan","name":"Failure","countryCode":"US","group_name":"Max","timestamp":"2026-04-14T07:12:25.961Z","status":404,"responseTime":640,"success":0,"error":"HTTP 404"},
{"id":156701,"url":"https://www.discoveryplus.com/ca/en","name":"Homepage","countryCode":"CA","group_name":"D+","timestamp":"2026-04-14T07:12:25.934Z","status":404,"responseTime":604,"success":0,"error":"HTTP 404"},
{"id":156700,"url":"https://www.max.com/movies","name":"Movie","countryCode":"US","group_name":"Max","timestamp":"2026-04-14T07:12:25.735Z","status":200,"responseTime":415,"success":1,"error":null},
{"id":156699,"url":"https://www.max.com/mx/es","name":"Homepage","countryCode":"MX","group_name":"Max","timestamp":"2026-04-14T07:12:25.695Z","status":200,"responseTime":369,"success":1,"error":null},
{"id":156698,"url":"https://www.max.com/movies","name":"Movie","countryCode":"MX","group_name":"Max","timestamp":"2026-04-14T07:12:25.683Z","status":200,"responseTime":355,"success":1,"error":null},
{"id":156697,"url":"https://www.max.com","name":"Homepage","countryCode":"US","group_name":"Max","timestamp":"2026-04-14T07:12:25.681Z","status":200,"responseTime":417,"success":1,"error":null},
{"id":156696,"url":"https://www.discoveryplus.com","name":"Homepage","countryCode":"US","group_name":"D+","timestamp":"2026-04-14T07:12:25.674Z","status":200,"responseTime":351,"success":1,"error":null},
{"id":156695,"url":"https://www.discoveryplus.com/ca/en/movies","name":"Movie","countryCode":"CA","group_name":"D+","timestamp":"2026-04-14T07:12:25.597Z","status":200,"responseTime":265,"success":1,"error":null},
{"id":156694,"url":"https://www.discoveryplus.com/movies","name":"Movie","countryCode":"US","group_name":"D+","timestamp":"2026-04-14T07:12:25.587Z","status":200,"responseTime":262,"success":1,"error":null},
{"id":156693,"url":"https://www.discoveryplus.com/ca/en/shows","name":"Show","countryCode":"CA","group_name":"D+","timestamp":"2026-04-14T05:36:50.124Z","status":200,"responseTime":1451,"success":1,"error":null},
{"id":156692,"url":"https://www.max.com/rohan","name":"Failure","countryCode":"US","group_name":"Max","timestamp":"2026-04-14T05:36:49.333Z","status":404,"responseTime":668,"success":0,"error":"HTTP 404"},
{"id":156691,"url":"https://www.discoveryplus.com/ca/en","name":"Homepage","countryCode":"CA","group_name":"D+","timestamp":"2026-04-14T05:36:49.129Z","status":404,"responseTime":457,"success":0,"error":"HTTP 404"},
{"id":156690,"url":"https://www.max.com/mx/es/shows","name":"Show","countryCode":"MX","group_name":"Max","timestamp":"2026-04-14T05:36:49.119Z","status":200,"responseTime":449,"success":1,"error":null},
{"id":156689,"url":"https://www.max.com/movies","name":"Movie","countryCode":"MX","group_name":"Max","timestamp":"2026-04-14T05:36:49.118Z","status":200,"responseTime":447,"success":1,"error":null},
{"id":156688,"url":"https://www.max.com","name":"Homepage","countryCode":"US","group_name":"Max","timestamp":"2026-04-14T05:36:49.114Z","status":200,"responseTime":505,"success":1,"error":null},
{"id":156687,"url":"https://www.max.com/mx/es","name":"Homepage","countryCode":"MX","group_name":"Max","timestamp":"2026-04-14T05:36:49.111Z","status":200,"responseTime":442,"success":1,"error":null},
{"id":156686,"url":"https://www.max.com/shows","name":"Show","countryCode":"US","group_name":"Max","timestamp":"2026-04-14T05:36:49.108Z","status":200,"responseTime":446,"success":1,"error":null},
{"id":156685,"url":"https://www.max.com/movies","name":"Movie","countryCode":"US","group_name":"Max","timestamp":"2026-04-14T05:36:49.101Z","status":200,"responseTime":437,"success":1,"error":null},
{"id":156684,"url":"https://www.discoveryplus.com/ca/en/movies","name":"Movie","countryCode":"CA","group_name":"D+","timestamp":"2026-04-14T05:36:48.993Z","status":200,"responseTime":319,"success":1,"error":null},
{"id":156683,"url":"https://www.discoveryplus.com","name":"Homepage","countryCode":"US","group_name":"D+","timestamp":"2026-04-14T05:36:48.972Z","status":200,"responseTime":306,"success":1,"error":null},
{"id":156682,"url":"https://www.discoveryplus.com/shows","name":"Show","countryCode":"US","group_name":"D+","timestamp":"2026-04-14T05:36:48.970Z","status":200,"responseTime":303,"success":1,"error":null},
{"id":156681,"url":"https://www.discoveryplus.com/movies","name":"Movie","countryCode":"US","group_name":"D+","timestamp":"2026-04-14T05:36:48.938Z","status":200,"responseTime":270,"success":1,"error":null},
{"id":156680,"url":"https://www.discoveryplus.com/ca/en/shows","name":"Show","countryCode":"CA","group_name":"D+","timestamp":"2026-04-14T03:24:58.858Z","status":200,"responseTime":1393,"success":1,"error":null},
{"id":156679,"url":"https://www.discoveryplus.com/ca/en","name":"Homepage","countryCode":"CA","group_name":"D+","timestamp":"2026-04-14T03:24:58.219Z","status":404,"responseTime":755,"success":0,"error":"HTTP 404"},
{"id":156678,"url":"https://www.max.com/mx/es/shows","name":"Show","countryCode":"MX","group_name":"Max","timestamp":"2026-04-14T03:24:58.122Z","status":200,"responseTime":660,"success":1,"error":null},
{"id":156677,"url":"https://www.max.com/rohan","name":"Failure","countryCode":"US","group_name":"Max","timestamp":"2026-04-14T03:24:57.993Z","status":404,"responseTime":538,"success":0,"error":"HTTP 404"},
{"id":156676,"url":"https://www.discoveryplus.com/ca/en/movies","name":"Movie","countryCode":"CA","group_name":"D+","timestamp":"2026-04-14T03:24:57.850Z","status":200,"responseTime":384,"success":1,"error":null},
{"id":156675,"url":"https://www.discoveryplus.com/movies","name":"Movie","countryCode":"US","group_name":"D+","timestamp":"2026-04-14T03:24:57.780Z","status":200,"responseTime":321,"success":1,"error":null},
{"id":156674,"url":"https://www.max.com/shows","name":"Show","countryCode":"US","group_name":"Max","timestamp":"2026-04-14T03:24:57.776Z","status":200,"responseTime":323,"success":1,"error":null},
{"id":156673,"url":"https://www.max.com/movies","name":"Movie","countryCode":"MX","group_name":"Max","timestamp":"2026-04-14T03:24:57.715Z","status":200,"responseTime":252,"success":1,"error":null},
{"id":156672,"url":"https://www.max.com","name":"Homepage","countryCode":"US","group_name":"Max","timestamp":"2026-04-14T03:24:57.711Z","status":200,"responseTime":312,"success":1,"error":null},
{"id":156671,"url":"https://www.max.com/mx/es","name":"Homepage","countryCode":"MX","group_name":"Max","timestamp":"2026-04-14T03:24:57.703Z","status":200,"responseTime":243,"success":1,"error":null},
{"id":156670,"url":"https://www.max.com/movies","name":"Movie","countryCode":"US","group_name":"Max","timestamp":"2026-04-14T03:24:57.697Z","status":200,"responseTime":243,"success":1,"error":null},
{"id":156669,"url":"https://www.discoveryplus.com/shows","name":"Show","countryCode":"US","group_name":"D+","timestamp":"2026-04-14T03:24:57.641Z","status":200,"responseTime":183,"success":1,"error":null},
{"id":156668,"url":"https://www.discoveryplus.com","name":"Homepage","countryCode":"US","group_name":"D+","timestamp":"2026-04-14T03:24:57.625Z","status":200,"responseTime":168,"success":1,"error":null}]
