[{"url":"https://www.max.com/rohan","name":"Failure","group_name":"Max","countryCode":"US","totalRequests":53,"successfulRequests":0,"failedRequests":53,"successRate":0.0,"averageResponseTime":774.0,"lastChecked":"2025-12-19T14:46:06.931Z","lastStatus":404},
{"url":"https://www.discoveryplus.com","name":"Homepage","group_name":"D+","countryCode":"US","totalRequests":53,"successfulRequests":53,"failedRequests":0,"successRate":100.0,"averageResponseTime":359.0,"lastChecked":"2025-12-19T14:46:06.270Z","lastStatus":200},
{"url":"https://www.discoveryplus.com/ca/en","name":"Homepage","group_name":"D+","countryCode":"CA","totalRequests":53,"successfulRequests":53,"failedRequests":0,"successRate":100.0,"averageResponseTime":455.0,"lastChecked":"2025-12-19T14:46:06.674Z","lastStatus":200},
{"url":"https://www.max.com","name":"Homepage","group_name":"Max","countryCode":"US","totalRequests":53,"successfulRequests":53,"failedRequests":0,"successRate":100.0,"averageResponseTime":498.0,"lastChecked":"2025-12-19T14:46:06.307Z","lastStatus":200},
{"url":"https://www.max.com/mx/es","name":"Homepage","group_name":"Max","countryCode":"MX","totalRequests":53,"successfulRequests":53,"failedRequests":0,"successRate":100.0,"averageResponseTime":496.0,"lastChecked":"2025-12-19T14:46:06.293Z","lastStatus":200},
{"url":"https://www.discoveryplus.com/ca/en/movies","name":"Movie","group_name":"D+","countryCode":"CA","totalRequests":53,"successfulRequests":52,"failedRequests":1,"successRate":98.1099999999999994,"averageResponseTime":783.0,"lastChecked":"2025-12-19T14:46:07.063Z","lastStatus":200},
{"url":"https://www.discoveryplus.com/movies","name":"Movie","group_name":"D+","countryCode":"US","totalRequests":53,"successfulRequests":53,"failedRequests":0,"successRate":100.0,"averageResponseTime":439.0,"lastChecked":"2025-12-19T14:46:06.262Z","lastStatus":200},
{"url":"https://www.max.com/movies","name":"Movie","group_name":"Max","countryCode":"MX","totalRequests":53,"successfulRequests":53,"failedRequests":0,"successRate":100.0,"averageResponseTime":552.0,"lastChecked":"2025-12-19T14:46:06.311Z","lastStatus":200},
{"url":"https://www.max.com/movies","name":"Movie","group_name":"Max","countryCode":"US","totalRequests":53,"successfulRequests":53,"failedRequests":0,"successRate":100.0,"averageResponseTime":520.0,"lastChecked":"2025-12-19T14:46:06.348Z","lastStatus":200},
{"url":"https://www.discoveryplus.com/ca/en/shows","name":"Show","group_name":"D+","countryCode":"CA","totalRequests":53,"successfulRequests":52,"failedRequests":1,"successRate":98.1099999999999994,"averageResponseTime":930.0,"lastChecked":"2025-12-19T14:46:06.946Z","lastStatus":200},
{"url":"https://www.discoveryplus.com/shows","name":"Show","group_name":"D+","countryCode":"US","totalRequests":53,"successfulRequests":53,"failedRequests":0,"successRate":100.0,"averageResponseTime":509.0,"lastChecked":"2025-12-19T14:46:06.216Z","lastStatus":200},
{"url":"https://www.max.com/mx/es/shows","name":"Show","group_name":"Max","countryCode":"MX","totalRequests":53,"successfulRequests":53,"failedRequests":0,"successRate":100.0,"averageResponseTime":795.0,"lastChecked":"2025-12-19T14:46:06.750Z","lastStatus":200},
{"url":"https://www.max.com/shows","name":"Show","group_name":"Max","countryCode":"US","totalRequests":53,"successfulRequests":53,"failedRequests":0,"successRate":100.0,"averageResponseTime":606.0,"lastChecked":"2025-12-19T14:46:06.683Z","lastStatus":200}]
