[{"url":"https://www.max.com/rohan","name":"Failure","group_name":"Max","countryCode":"US","totalRequests":64,"successfulRequests":0,"failedRequests":64,"successRate":0.0,"averageResponseTime":701.0,"lastChecked":"2025-10-07T16:19:26.446Z","lastStatus":404},
{"url":"https://www.discoveryplus.com","name":"Homepage","group_name":"D+","countryCode":"US","totalRequests":64,"successfulRequests":64,"failedRequests":0,"successRate":100.0,"averageResponseTime":343.0,"lastChecked":"2025-10-07T16:19:26.076Z","lastStatus":200},
{"url":"https://www.discoveryplus.com/ca/en","name":"Homepage","group_name":"D+","countryCode":"CA","totalRequests":64,"successfulRequests":64,"failedRequests":0,"successRate":100.0,"averageResponseTime":450.0,"lastChecked":"2025-10-07T16:19:26.153Z","lastStatus":200},
{"url":"https://www.max.com","name":"Homepage","group_name":"Max","countryCode":"US","totalRequests":64,"successfulRequests":64,"failedRequests":0,"successRate":100.0,"averageResponseTime":547.0,"lastChecked":"2025-10-07T16:19:26.363Z","lastStatus":200},
{"url":"https://www.max.com/mx/es","name":"Homepage","group_name":"Max","countryCode":"MX","totalRequests":64,"successfulRequests":64,"failedRequests":0,"successRate":100.0,"averageResponseTime":473.0,"lastChecked":"2025-10-07T16:19:26.324Z","lastStatus":200},
{"url":"https://www.discoveryplus.com/ca/en/movies","name":"Movie","group_name":"D+","countryCode":"CA","totalRequests":64,"successfulRequests":64,"failedRequests":0,"successRate":100.0,"averageResponseTime":513.0,"lastChecked":"2025-10-07T16:19:26.072Z","lastStatus":200},
{"url":"https://www.discoveryplus.com/movies","name":"Movie","group_name":"D+","countryCode":"US","totalRequests":64,"successfulRequests":64,"failedRequests":0,"successRate":100.0,"averageResponseTime":440.0,"lastChecked":"2025-10-07T16:19:26.148Z","lastStatus":200},
{"url":"https://www.max.com/movies","name":"Movie","group_name":"Max","countryCode":"MX","totalRequests":64,"successfulRequests":64,"failedRequests":0,"successRate":100.0,"averageResponseTime":526.0,"lastChecked":"2025-10-07T16:19:26.123Z","lastStatus":200},
{"url":"https://www.max.com/movies","name":"Movie","group_name":"Max","countryCode":"US","totalRequests":64,"successfulRequests":64,"failedRequests":0,"successRate":100.0,"averageResponseTime":498.0,"lastChecked":"2025-10-07T16:19:26.108Z","lastStatus":200},
{"url":"https://www.discoveryplus.com/ca/en/shows","name":"Show","group_name":"D+","countryCode":"CA","totalRequests":64,"successfulRequests":64,"failedRequests":0,"successRate":100.0,"averageResponseTime":624.0,"lastChecked":"2025-10-07T16:19:25.939Z","lastStatus":200},
{"url":"https://www.discoveryplus.com/shows","name":"Show","group_name":"D+","countryCode":"US","totalRequests":64,"successfulRequests":64,"failedRequests":0,"successRate":100.0,"averageResponseTime":499.0,"lastChecked":"2025-10-07T16:19:26.028Z","lastStatus":200},
{"url":"https://www.max.com/mx/es/shows","name":"Show","group_name":"Max","countryCode":"MX","totalRequests":64,"successfulRequests":64,"failedRequests":0,"successRate":100.0,"averageResponseTime":805.0,"lastChecked":"2025-10-07T16:19:26.075Z","lastStatus":200},
{"url":"https://www.max.com/shows","name":"Show","group_name":"Max","countryCode":"US","totalRequests":64,"successfulRequests":64,"failedRequests":0,"successRate":100.0,"averageResponseTime":602.0,"lastChecked":"2025-10-07T16:19:26.339Z","lastStatus":200}]
