[{"url":"https://www.max.com/rohan","name":"Failure","group_name":"Max","countryCode":"US","totalRequests":68,"successfulRequests":0,"failedRequests":68,"successRate":0.0,"averageResponseTime":908.0,"lastChecked":"2025-08-23T18:19:32.967Z","lastStatus":404},
{"url":"https://www.discoveryplus.com","name":"Homepage","group_name":"D+","countryCode":"US","totalRequests":68,"successfulRequests":68,"failedRequests":0,"successRate":100.0,"averageResponseTime":465.0,"lastChecked":"2025-08-23T18:19:32.797Z","lastStatus":200},
{"url":"https://www.discoveryplus.com/ca/en","name":"Homepage","group_name":"D+","countryCode":"CA","totalRequests":68,"successfulRequests":68,"failedRequests":0,"successRate":100.0,"averageResponseTime":502.0,"lastChecked":"2025-08-23T18:19:32.728Z","lastStatus":200},
{"url":"https://www.max.com","name":"Homepage","group_name":"Max","countryCode":"US","totalRequests":68,"successfulRequests":67,"failedRequests":1,"successRate":98.5300000000000011,"averageResponseTime":683.0,"lastChecked":"2025-08-23T18:19:32.674Z","lastStatus":200},
{"url":"https://www.max.com/mx/es","name":"Homepage","group_name":"Max","countryCode":"MX","totalRequests":68,"successfulRequests":68,"failedRequests":0,"successRate":100.0,"averageResponseTime":615.0,"lastChecked":"2025-08-23T18:19:32.654Z","lastStatus":200},
{"url":"https://www.discoveryplus.com/ca/en/movies","name":"Movie","group_name":"D+","countryCode":"CA","totalRequests":68,"successfulRequests":66,"failedRequests":2,"successRate":97.0600000000000022,"averageResponseTime":529.0,"lastChecked":"2025-08-23T18:19:32.647Z","lastStatus":200},
{"url":"https://www.discoveryplus.com/movies","name":"Movie","group_name":"D+","countryCode":"US","totalRequests":68,"successfulRequests":68,"failedRequests":0,"successRate":100.0,"averageResponseTime":473.0,"lastChecked":"2025-08-23T18:19:32.620Z","lastStatus":200},
{"url":"https://www.max.com/movies","name":"Movie","group_name":"Max","countryCode":"MX","totalRequests":68,"successfulRequests":68,"failedRequests":0,"successRate":100.0,"averageResponseTime":589.0,"lastChecked":"2025-08-23T18:19:32.678Z","lastStatus":200},
{"url":"https://www.max.com/movies","name":"Movie","group_name":"Max","countryCode":"US","totalRequests":68,"successfulRequests":68,"failedRequests":0,"successRate":100.0,"averageResponseTime":586.0,"lastChecked":"2025-08-23T18:19:32.669Z","lastStatus":200},
{"url":"https://www.discoveryplus.com/ca/en/shows","name":"Show","group_name":"D+","countryCode":"CA","totalRequests":68,"successfulRequests":68,"failedRequests":0,"successRate":100.0,"averageResponseTime":661.0,"lastChecked":"2025-08-23T18:19:32.973Z","lastStatus":200},
{"url":"https://www.discoveryplus.com/shows","name":"Show","group_name":"D+","countryCode":"US","totalRequests":68,"successfulRequests":68,"failedRequests":0,"successRate":100.0,"averageResponseTime":541.0,"lastChecked":"2025-08-23T18:19:32.637Z","lastStatus":200},
{"url":"https://www.max.com/mx/es/shows","name":"Show","group_name":"Max","countryCode":"MX","totalRequests":68,"successfulRequests":67,"failedRequests":1,"successRate":98.5300000000000011,"averageResponseTime":786.0,"lastChecked":"2025-08-23T18:19:32.660Z","lastStatus":200},
{"url":"https://www.max.com/shows","name":"Show","group_name":"Max","countryCode":"US","totalRequests":68,"successfulRequests":67,"failedRequests":1,"successRate":98.5300000000000011,"averageResponseTime":646.0,"lastChecked":"2025-08-23T18:19:32.650Z","lastStatus":200}]
