[{"url":"https://www.max.com/rohan","name":"Failure","group_name":"Max","countryCode":"US","totalRequests":24,"successfulRequests":0,"failedRequests":24,"successRate":0.0,"averageResponseTime":885.0,"lastChecked":"2026-02-27T00:03:02.519Z","lastStatus":404},
{"url":"https://www.discoveryplus.com","name":"Homepage","group_name":"D+","countryCode":"US","totalRequests":24,"successfulRequests":24,"failedRequests":0,"successRate":100.0,"averageResponseTime":367.0,"lastChecked":"2026-02-27T00:03:02.023Z","lastStatus":200},
{"url":"https://www.discoveryplus.com/ca/en","name":"Homepage","group_name":"D+","countryCode":"CA","totalRequests":24,"successfulRequests":24,"failedRequests":0,"successRate":100.0,"averageResponseTime":653.0,"lastChecked":"2026-02-27T00:03:02.332Z","lastStatus":200},
{"url":"https://www.max.com","name":"Homepage","group_name":"Max","countryCode":"US","totalRequests":24,"successfulRequests":24,"failedRequests":0,"successRate":100.0,"averageResponseTime":578.0,"lastChecked":"2026-02-27T00:03:02.214Z","lastStatus":200},
{"url":"https://www.max.com/mx/es","name":"Homepage","group_name":"Max","countryCode":"MX","totalRequests":24,"successfulRequests":24,"failedRequests":0,"successRate":100.0,"averageResponseTime":532.0,"lastChecked":"2026-02-27T00:03:02.406Z","lastStatus":200},
{"url":"https://www.discoveryplus.com/ca/en/movies","name":"Movie","group_name":"D+","countryCode":"CA","totalRequests":24,"successfulRequests":24,"failedRequests":0,"successRate":100.0,"averageResponseTime":721.0,"lastChecked":"2026-02-27T00:03:02.446Z","lastStatus":200},
{"url":"https://www.discoveryplus.com/movies","name":"Movie","group_name":"D+","countryCode":"US","totalRequests":24,"successfulRequests":24,"failedRequests":0,"successRate":100.0,"averageResponseTime":406.0,"lastChecked":"2026-02-27T00:03:02.691Z","lastStatus":200},
{"url":"https://www.max.com/movies","name":"Movie","group_name":"Max","countryCode":"MX","totalRequests":24,"successfulRequests":24,"failedRequests":0,"successRate":100.0,"averageResponseTime":533.0,"lastChecked":"2026-02-27T00:03:02.448Z","lastStatus":200},
{"url":"https://www.max.com/movies","name":"Movie","group_name":"Max","countryCode":"US","totalRequests":24,"successfulRequests":24,"failedRequests":0,"successRate":100.0,"averageResponseTime":557.0,"lastChecked":"2026-02-27T00:03:02.497Z","lastStatus":200},
{"url":"https://www.discoveryplus.com/ca/en/shows","name":"Show","group_name":"D+","countryCode":"CA","totalRequests":24,"successfulRequests":24,"failedRequests":0,"successRate":100.0,"averageResponseTime":1040.0,"lastChecked":"2026-02-27T00:03:02.893Z","lastStatus":200},
{"url":"https://www.discoveryplus.com/shows","name":"Show","group_name":"D+","countryCode":"US","totalRequests":24,"successfulRequests":24,"failedRequests":0,"successRate":100.0,"averageResponseTime":449.0,"lastChecked":"2026-02-27T00:03:02.027Z","lastStatus":200},
{"url":"https://www.max.com/mx/es/shows","name":"Show","group_name":"Max","countryCode":"MX","totalRequests":24,"successfulRequests":24,"failedRequests":0,"successRate":100.0,"averageResponseTime":778.0,"lastChecked":"2026-02-27T00:03:02.391Z","lastStatus":200},
{"url":"https://www.max.com/shows","name":"Show","group_name":"Max","countryCode":"US","totalRequests":24,"successfulRequests":24,"failedRequests":0,"successRate":100.0,"averageResponseTime":575.0,"lastChecked":"2026-02-27T00:03:02.751Z","lastStatus":200}]
