[{"url":"https://www.max.com/rohan","name":"Failure","group_name":"Max","countryCode":"US","totalRequests":43,"successfulRequests":0,"failedRequests":43,"successRate":0.0,"averageResponseTime":771.0,"lastChecked":"2026-03-08T15:46:02.620Z","lastStatus":404},
{"url":"https://www.discoveryplus.com","name":"Homepage","group_name":"D+","countryCode":"US","totalRequests":43,"successfulRequests":43,"failedRequests":0,"successRate":100.0,"averageResponseTime":349.0,"lastChecked":"2026-03-08T15:46:02.247Z","lastStatus":200},
{"url":"https://www.discoveryplus.com/ca/en","name":"Homepage","group_name":"D+","countryCode":"CA","totalRequests":43,"successfulRequests":43,"failedRequests":0,"successRate":100.0,"averageResponseTime":553.0,"lastChecked":"2026-03-08T15:46:02.286Z","lastStatus":200},
{"url":"https://www.max.com","name":"Homepage","group_name":"Max","countryCode":"US","totalRequests":43,"successfulRequests":43,"failedRequests":0,"successRate":100.0,"averageResponseTime":543.0,"lastChecked":"2026-03-08T15:46:02.358Z","lastStatus":200},
{"url":"https://www.max.com/mx/es","name":"Homepage","group_name":"Max","countryCode":"MX","totalRequests":43,"successfulRequests":43,"failedRequests":0,"successRate":100.0,"averageResponseTime":514.0,"lastChecked":"2026-03-08T15:46:02.401Z","lastStatus":200},
{"url":"https://www.discoveryplus.com/ca/en/movies","name":"Movie","group_name":"D+","countryCode":"CA","totalRequests":43,"successfulRequests":43,"failedRequests":0,"successRate":100.0,"averageResponseTime":554.0,"lastChecked":"2026-03-08T15:46:02.346Z","lastStatus":200},
{"url":"https://www.discoveryplus.com/movies","name":"Movie","group_name":"D+","countryCode":"US","totalRequests":43,"successfulRequests":43,"failedRequests":0,"successRate":100.0,"averageResponseTime":347.0,"lastChecked":"2026-03-08T15:46:02.251Z","lastStatus":200},
{"url":"https://www.max.com/movies","name":"Movie","group_name":"Max","countryCode":"MX","totalRequests":43,"successfulRequests":43,"failedRequests":0,"successRate":100.0,"averageResponseTime":528.0,"lastChecked":"2026-03-08T15:46:02.386Z","lastStatus":200},
{"url":"https://www.max.com/movies","name":"Movie","group_name":"Max","countryCode":"US","totalRequests":43,"successfulRequests":43,"failedRequests":0,"successRate":100.0,"averageResponseTime":495.0,"lastChecked":"2026-03-08T15:46:02.362Z","lastStatus":200},
{"url":"https://www.discoveryplus.com/ca/en/shows","name":"Show","group_name":"D+","countryCode":"CA","totalRequests":43,"successfulRequests":43,"failedRequests":0,"successRate":100.0,"averageResponseTime":737.0,"lastChecked":"2026-03-08T15:46:02.287Z","lastStatus":200},
{"url":"https://www.discoveryplus.com/shows","name":"Show","group_name":"D+","countryCode":"US","totalRequests":43,"successfulRequests":43,"failedRequests":0,"successRate":100.0,"averageResponseTime":388.0,"lastChecked":"2026-03-08T15:46:02.288Z","lastStatus":200},
{"url":"https://www.max.com/mx/es/shows","name":"Show","group_name":"Max","countryCode":"MX","totalRequests":43,"successfulRequests":43,"failedRequests":0,"successRate":100.0,"averageResponseTime":784.0,"lastChecked":"2026-03-08T15:46:03.353Z","lastStatus":200},
{"url":"https://www.max.com/shows","name":"Show","group_name":"Max","countryCode":"US","totalRequests":43,"successfulRequests":43,"failedRequests":0,"successRate":100.0,"averageResponseTime":549.0,"lastChecked":"2026-03-08T15:46:02.403Z","lastStatus":200}]
